{
  "name": "asche-banana-dark",

  "cursorColor": "#e0cd85",
  "selectionBackground": "#847748",

  "background": "#211712",
  "foreground": "#e0cd85",

  "black": "#422e24",
  "blue": "#b89494",
  "cyan": "#f4b371",
  "green": "#c9a782",
  "purple": "#f4d371",
  "red": "#ecec79",
  "white": "#e0cd85",
  "yellow": "#b8af94",
  "brightBlack": "#422e24",
  "brightBlue": "#b89494",
  "brightCyan": "#f4b371",
  "brightGreen": "#c9a782",
  "brightPurple": "#f4d371",
  "brightRed": "#ecec79",
  "brightWhite": "#e0cd85",
  "brightYellow": "#b8af94"
}
