{
  "name": "finstey",

  "cursorColor": "#f4e6bd",
  "selectionBackground": "#6e6581",

  "background": "#25222b",
  "foreground": "#f4e6bd",

  "black": "#3d3847",
  "blue": "#e085b3",
  "cyan": "#76efef",
  "green": "#b376ef",
  "purple": "#76b3ef",
  "red": "#7676ef",
  "white": "#f4e6bd",
  "yellow": "#e085e0",
  "brightBlack": "#3d3847",
  "brightBlue": "#e085b3",
  "brightCyan": "#76efef",
  "brightGreen": "#b376ef",
  "brightPurple": "#76b3ef",
  "brightRed": "#7676ef",
  "brightWhite": "#f4e6bd",
  "brightYellow": "#e085e0"
}
